qtools3/__init__.py
qtools3/__version__.py
qtools3/cli.py
qtools3/constants.py
qtools3/convert.py
qtools3/errors.py
qtools3/gui.py
qtools3/gui_config.py
qtools3/xform.py
qtools3/xlsform.py
qtools3-0.3.6.dist-info/LICENSE.txt
qtools3-0.3.6.dist-info/METADATA
qtools3-0.3.6.dist-info/WHEEL
qtools3-0.3.6.dist-info/entry_points.txt
qtools3-0.3.6.dist-info/top_level.txt
qtools3-0.3.6.dist-info/RECORD
