Metadata-Version: 2.1
Name: qtools3
Version: 0.3.6
Summary: Convert ODK files from XlsForm to Xform.
Home-page: https://github.com/PMA-2020/qtools3
Author: James Pringle
Author-email: jpringle@jhu.edu
License: MIT
Platform: UNKNOWN
Classifier: License :: OSI Approved :: MIT License
Classifier: Programming Language :: Python
Classifier: Programming Language :: Python :: 3
Classifier: Programming Language :: Python :: 3.6
Classifier: Programming Language :: Python :: Implementation :: CPython
Requires-Python: >=3.6.0
Requires-Dist: pmaxform3
